docbuild/__init__.py
docbuild/constants.py
docbuild/graph.py
docbuild/hocr_parser.py
docbuild/page_creator.py
docbuild/textract_parser.py
docbuild/utils.py
docbuild/paragraph_detection/__init__.py
docbuild/paragraph_detection/constants.py
docbuild/paragraph_detection/paragraph_extractor.py
docbuild/paragraph_detection/paragraph_sorter.py
docbuild/paragraph_detection/two_columns.py
docbuild/visual_detection/__init__.py
docbuild/visual_detection/bordered_table_extraction.py
docbuild/visual_detection/borderless_table_extraction.py
docbuild/visual_detection/constants.py
docbuild/visual_detection/vis_line_detection.py
docbuild-0.1.115.dist-info/METADATA
docbuild-0.1.115.dist-info/WHEEL
docbuild-0.1.115.dist-info/top_level.txt
docbuild-0.1.115.dist-info/RECORD
